djsmartcache/__init__.py
djsmartcache/apps.py
djsmartcache/conf.py
djsmartcache/decorators.py
djsmartcache/listener.py
djsmartcache/manager.py
djsmartcache/middleware.py
djsmartcache/signals.py
djsmartcache/utils.py
djsmartcache-0.13.12.dist-info/licenses/LICENSE
djsmartcache-0.13.12.dist-info/METADATA
djsmartcache-0.13.12.dist-info/WHEEL
djsmartcache-0.13.12.dist-info/top_level.txt
djsmartcache-0.13.12.dist-info/RECORD
