Metadata-Version: 2.4
Name: djsmartcache
Version: 0.13.12
Summary: Distributed cache consistency layer for Django using Redis
Author: Kuntal Roy
License: MIT
Requires-Python: >=3.8
License-File: LICENSE
Dynamic: license-file
